pitrix/__init__.py
pitrix/_pitrix.py
pitrix/base/__init__.py
pitrix/base/base_api.py
pitrix/base/base_assert.py
pitrix/cli.py
pitrix/constants/__init__.py
pitrix/constants/constants.py
pitrix/constants/path.py
pitrix/database/__init__.py
pitrix/database/base_db.py
pitrix/database/cache.py
pitrix/database/mysql.py
pitrix/database/pitrix_table.py
pitrix/database/sqlite.py
pitrix/exceptions.py
pitrix/extension/__init__.py
pitrix/extension/allure_report.py
pitrix/extension/models.py
pitrix/extension/read_swagger.py
pitrix/extension/record.py
pitrix/extension/retry.py
pitrix/extension/swagger2yaml.py
pitrix/extension/template.py
pitrix/extension/wechat.py
pitrix/fixture.py
pitrix/runner.py
pitrix/scaffold.py
pitrix/templates/apis/__init__.py.temp
pitrix/templates/apis/base.py.temp
pitrix/templates/apis/common/__init__.py.temp
pitrix/templates/apis/common/base.py.temp
pitrix/templates/apis/common/context.py.temp
pitrix/templates/apis/common/manager.py.temp
pitrix/templates/apis/computer/__init__.py.temp
pitrix/templates/apis/network/__init__.py.temp
pitrix/templates/apis/network/router_table.py.temp
pitrix/templates/apis/network/vxnet.py.temp
pitrix/templates/config/config.yaml.temp
pitrix/templates/config/notification.yaml.temp
pitrix/templates/conftest.py.temp
pitrix/templates/lib/__init__.py.temp
pitrix/templates/lib/common/__init__.py.temp
pitrix/templates/lib/common/rest_client.py.temp
pitrix/templates/lib/common/waiters.py.temp
pitrix/templates/login.py.temp
pitrix/templates/public/__init__.py.temp
pitrix/templates/public/path.py.temp
pitrix/templates/pytest.ini.temp
pitrix/templates/run.py.temp
pitrix/templates/testcases/__init__.py.temp
pitrix/templates/testcases/test_demo.py.temp
pitrix/templates/utils/__init__.py.temp
pitrix/templates/utils/common.py.temp
pitrix/templates/utils/decorator.py.temp
pitrix/utils/__init__.py
pitrix/utils/allure_attach.py
pitrix/utils/common.py
pitrix/utils/csvutils.py
pitrix/utils/decorator.py
pitrix/utils/emailutils.py
pitrix-0.0.24.dist-info/LICENSE
pitrix-0.0.24.dist-info/METADATA
pitrix-0.0.24.dist-info/WHEEL
pitrix-0.0.24.dist-info/entry_points.txt
pitrix-0.0.24.dist-info/RECORD
